{"keys": ["190", "", "60", "142", "53"], "data": {"60": {"REAL": 4.366244, "INDEX": 0.879579426324, "NAME": "Finland", "AREA": 30459, "REGION": 150, "LON": 26.272, "SUBREGION": 154, "ISO3": "FIN", "ISO2": "FI", "FIPS": "FI", "UN": 246, "LAT": 64.504, "POP2005": 5246004}, "142": {"REAL": -999.99, "INDEX": -999.99, "NAME": "\u00c5land Islands", "AREA": 0, "REGION": 150, "LON": 19.952, "SUBREGION": 154, "ISO3": "ALA", "ISO2": "AX", "FIPS": "", "UN": 248, "LAT": 60.198, "POP2005": 0}, "190": {"REAL": 6.312298, "INDEX": 1.2716118141, "NAME": "Sweden", "AREA": 41033, "REGION": 150, "LON": 15.27, "SUBREGION": 154, "ISO3": "SWE", "ISO2": "SE", "FIPS": "SW", "UN": 752, "LAT": 62.011, "POP2005": 9038049}, "53": {"REAL": 7.198966, "INDEX": 1.45023099589, "NAME": "Estonia", "AREA": 4239, "REGION": 150, "LON": 25.793, "SUBREGION": 154, "ISO3": "EST", "ISO2": "EE", "FIPS": "EN", "UN": 233, "LAT": 58.674, "POP2005": 1344312}}, "grid": ["   !!!!!!!!!!!!!!!!!!!!!!!!!!!!!!!!!!!!!!!!!!!!!!!!!!!##########", "    !!!!!!!!!!!!!!!!!!!!!!!!!!!!!!!!!!!!!!!!!!!!!!!!############", "    !!!!!!!!!!!!!!!!!!!!!!!!!!!!!!!!!!!!!!!!!!!!!!!!!###########", "    !!!!!!!!!!!!!!!!!!!!!!!!!!!!!!!!!!!!!!!!!!!!!!!!!###########", "     !!!!!!!!!!!!!!!!!!!!!!!!!!!!!!!!!!!!!!!!!!!!!!!!###########", "   !!!!!!!!!!!!!!!!!!!!!!!!!!!!!!!!!!!!!!!!!!!!!!!!!!###########", "    !!!!!!!!!!!!!!!!!!!!!!!!!!!!!!!!!!!!!!!!!!!!!!!!!###########", "     !!!!!!!!!!!!!!!!!!!!!!!!!!!!!!!!!!!!!!!!!!!!!!!!###########", "    !!!!!!!!!!!!!!!!!!!!!!!!!!!!!!!!!!!!!!!!!!!!!!!!!###########", "    !!!!!!!!!!!!!!!!!!!!!!!!!!!!!!!!!!!!!!!!!!!!!!!!############", "    !!!!!!!!!!!!!!!!!!!!!!!!!!!!!!!!!!!!!!!!!!!!!!!!############", "    !!!!!!!!!!!!!!!!!!!!!!!!!!!!!!!!!!!!!!!!!!!!!!!!############", "    !!!!!!!!!!!!!!!!!!!!!!!!!!!!!!!!!!!!!!!!!!!!!!!!############", "    !!!!!!!!!!!!!!!!!!!!!!!!!!!!!!!!!!!!!!!!!!!!!!!!############", "    !!!!!!!!!!!!!!!!!!!!!!!!!!!!!!!!!!!!!!!!!!!!!!!!############", "    !!!!!!!!!!!!!!!!!!!!!!!!!!!!!!!!!!!!!!!!!!!!!!##############", "    !!!!!!!!!!!!!!!!!!!!!!!!!!!!!!!!!!!!!!!!!!!!!!##############", "     !!!!!!!!!!!!!!!!!!!!!!!!!!!!!!!!!!!!!!!!!!!!!##############", "     !!!!!!!!!!!!!!!!!!!!!!!!!!!!!!!!!!!!!!!!!!!!!!#############", "     !!!!!!!!!!!!!!!!!!!!!!!!!!!!!!!!!!!!!!!!!!!!!!#############", "     !!!!!!!!!!!!!!!!!!!!!!!!!!!!!!!!!!!!!!!!!!!!!!#############", "     !!!!!!!!!!!!!!!!!!!!!!!!!!!!!!!!!!!!!!!!!!!!!!#############", "      !!!!!!!!!!!!!!!!!!!!!!!!!!!!!!!!!!!!!!!!!!!!!#############", "         !!!!!!!!!!!!!!!!!!!!!!!!!!!!!!!!!!!!!!!!###############", "         !   !!!!!!!!!!!!!!!!!!!!!!!!!!!!!!!!!!!!!#!############", "         !    !!!!!!!!!!!!!!!!!!!!!!!!!!!!!!!!!!!!###!#!########", "              !!! !!!!!!!!!!!!!!!!!!!!!!!!!!!!!!!!###!!##!######", "               !!  !!!!!!!!!!!!!!!!!!!!!!!!!!!!!!!!!!!!###!#####", "               !!  !!!!!!!!!!!!!!!$!!!!!!!!!!!!!!!!!!!!!##!!!###", "                   !!!!!!!!!!!!!!$$$$!!!!!!!!!!!!!!!!!!!###!!!!!", "                    !!!!!!!!!!!!!!$$$$!!!!!!!!!!!!!!!!!!!##!#!##", "                    !!!!!!!!!!!!$$!$$$$!$!!!!!!!!!!!!!!!!!!####!", "                    !!!!!!!!!!$$$$$$!$$$$!!!!!!!!!!!!!!!!!!!!#!#", "                  !!!!!!!!!!!!$$$$$$!$$!$!!!!!!!!!##!!!#####!#!#", "                     !!!!!!!!!$$$$$$$!$!!!!!!!!!!!!#!####!#!!!!#", "                       !!!!!!!!!!$$$$!$$!!!!!!!!!!!!!###!!!!!!!#", "                       !!!!!!!!!!!!$$$$!!!!!!!!!!!!!!!!!!!!!!!##", "                       !!!!!!!!!!!!$$$$!!!!!!!!!!!!!!!!!!!!!!!##", "                        !!!!!!!!!!!!!!$!!!!!!!!!!!!!!!!!!!!!!!!!", "                         !!!!!!!!!!!!!!!!!!!!!!!!!!!!!!!!!!!!!!!", "                          !!!!!!!!!!!!!!!!!!!!!!!!!!!!!!!!!!!!!!", "                          !!!!!!!!!!!!!!!!!!!!!!!!!!!!!!!!!!!!!!", "                         !!!!!!!!!!!!!!!!!!!!!!!!!!!!!!!!!!!!!!!", "        !                 !!!!!!!!!!!!!!!!!!!!!!!!!!!!!!!!!!!!!!", "                         !!!!!!!!!!!!!!!!!!!!!!!!!!!!!!!!!!!!!!!", "                      !!!!!!!!!!!!!!!!!!!!!!!!!!!!!!!!!!!!!!!!!!", "                      !!!!!!!!!!!!!!!!!!!!!!!!!!!!!!!!!!!!!!!!!!", "                     !!!!!!!!!!!!!!!!!!!!!!!!!!!!!!!!!!!!!!!!!!!", "!                     !!!!!!!!!!!!!!!!!!!!!!!!!!!!!!!!!!!!!!!!!!", " !!!!  !          ! !!!!!!!!!!!!!!!!!!!!!!!!!!!!!!!!!!!!!!!!!!!!", "     !!!         !  !!!!!!!!!!!!!!!!!!!!!!!!!!!!!!!!!!!!!!!!!!!!", "      !       !  !  !!!!!!!!!!!!!!!!!!!!!!!!!!!!!!!!!!!!!!!!!!!!", "      !!             !!!!!!!!!!!!!!!!!!!!!!!!!!!!!!!!!!!!!!!!!!!", "           !         !!!!!!!!!!!!!!!!!!!!!!!!!!!!!!!!!!!!!!!!!!!", "                 !   !!!!!!!!!!!!!!!!!!!!!!!!!!!!!!!!!!!!!!!!!!!", "                 !! !!!!!!!!!!!!!!!!!!!!!!!!!!!!!!!!!!!!!!!!!!!!", "                 !!!!!!!!!!!!!!!!!!!!!!!!!!!!!!!!!!!!!!!!!!!!!!!", "         !       ! !!!!!!!!!!!!!!!!!!!!!!!!!!!!!!!!!!!!!!!!!!!!!", "         !     !!  !!!!!!!!!!!!!!!!!!!!!!!!!!!!!!!!!!!!!!!!!!!!!", "              !!! !!!!!!!!!!!!!!!!!!!!!!!!!!!!!!!!!!!!!!!!!!!!!!", "             !!!!!!!!!!!!!!!!!!!!!!!!!!!!!!!!!!!!!!!!!!!!!!!!!!!", "             !!!!!!!!!!!!!!!!!!!!!!!!!!!!!!!!!!!!!!!!!!!!!!%%%%%", "          ! !!!!!!!!!!!!!!!!!!!!!!!!!!!!!!!!!!!!!!!!!!!!!!!!%%%%", "         !!!!!!!!!!!!!!!!!!!!!!!!!!!!!!!!!!!!!!!!!!!!!!!!!!!!!!%"]}