{"keys": ["", "235", "13", "78", "48", "173"], "data": {"235": {"1990": 0, "Indicator": "CO2 emissions (metric tons per capita)", "UN": 796, "NAME": "Turks and Caicos Islands", "AREA": 0, "1965": 0, "REGION": 19, "LON": -71.95, "SUBREGION": 29, "ISO3": "TCA", "ISO2": "TC", "FIPS": "TK", "Indicato_1": "EN.ATM.CO2E.PC", "LAT": 21.902, "2011": 6.010339, "POP2005": 24459}, "13": {"1990": 7.610436, "Indicator": "CO2 emissions (metric tons per capita)", "UN": 44, "NAME": "Bahamas", "AREA": 1001, "1965": 9.399946, "REGION": 19, "LON": -78.014, "SUBREGION": 29, "ISO3": "BHS", "ISO2": "BS", "FIPS": "BF", "Indicato_1": "EN.ATM.CO2E.PC", "LAT": 24.628, "2011": 5.205238, "POP2005": 323295}, "173": {"1990": 0, "Indicator": "CO2 emissions (metric tons per capita)", "UN": 630, "NAME": "Puerto Rico", "AREA": 887, "1965": 0, "REGION": 19, "LON": -66.466, "SUBREGION": 29, "ISO3": "PRI", "ISO2": "PR", "FIPS": "RQ", "Indicato_1": "EN.ATM.CO2E.PC", "LAT": 18.221, "2011": 0, "POP2005": 3946779}, "48": {"1990": 1.273938, "Indicator": "CO2 emissions (metric tons per capita)", "UN": 214, "NAME": "Dominican Republic", "AREA": 4838, "1965": 0.396839, "REGION": 19, "LON": -70.729, "SUBREGION": 29, "ISO3": "DOM", "ISO2": "DO", "FIPS": "DR", "Indicato_1": "EN.ATM.CO2E.PC", "LAT": 19.015, "2011": 2.156995, "POP2005": 9469601}, "78": {"1990": 0.139767, "Indicator": "CO2 emissions (metric tons per capita)", "UN": 332, "NAME": "Haiti", "AREA": 2756, "1965": 0.071193, "REGION": 19, "LON": -72.278, "SUBREGION": 29, "ISO3": "HTI", "ISO2": "HT", "FIPS": "HA", "Indicato_1": "EN.ATM.CO2E.PC", "LAT": 19.142, "2011": 0.220396, "POP2005": 9296291}}, "grid": ["            !!!                                                 ", "         !   !!!!                                               ", "         !!    !!!                                              ", "        !         !!                                            ", "                                                                ", " ##                                                             ", " #                                                              ", "                                                                ", "##                                                              ", "##                                                              ", "##                                                              ", "#                                                               ", "                                                                ", "                                                                ", "                                                                ", "                                                                ", "                                                                ", "                                                                ", "                                                                ", "                                                                ", "                                                                ", "                                                                ", "                                                                ", "  $$$$                                                          ", "    $$                                                          ", "$$$$$$$         %%%%%  %%%%                                     ", "$$$$$$$$$      %%%%%%%%%%%%%% %                                 ", "$$$$$$$$$$$$$$$$%%%%%%%%%%%%%%%%                                ", "$$$$$$$$$$$$$$$$%%%%%%%%%%%%%%%%%%%%%%                          ", "  $$$$$$$$$$$$$$$%%%%%%%%%%%%%%%%%%%%%                          ", "    $$$$$$$$$$$$$%%%%%%%%%%%%%%%%%%%%%                          ", "     $$$$$$$$$$$$%%%%%%%%%%%%%%%%%%%%%      %                   ", "    $$$$$$$$$$$$%%%%%%%%%%%%%%%%%%%%%%%%%%%%%%                  ", "    $$$$$$$$$$$$$$%%%%%%%%%%%%%%%%%%%%%%%%%%%                   ", "    $$$$$$$$$$$$$$%%%%%%%%%%%%%%%%%%%%%%                        ", "    $$$$$$$$$$$$$%%%%%%%%%%%%%%%%%%%%%%%%%%%   %                ", "$   $$$$$$$$$$$$%%%%%%%%%%%%%%%%%%%%%%%%%%%%%%%%%%%             ", "$$$   $$$$$$$$$$$%%%%%%%%%%%%%%%%%%%%%%%%%%%%%%%%%%%            ", "$$$$  $$$$$$$$$$$%%%%%%%%%%%%%%%%%%%%%%%%%%%%%%%%%%%%           ", "  $$   $$$$$$$$$$%%%%%%%%%%%%%%%%%%%%%%%%%%%%%%%%%%%%%          ", "         $$$$$$$%%%%%%%%%%%%%%%%%%%%%%%%%%%%%%%%%%%%%%%         ", "      $$$$$$$$%%%%%%%%%%%%%%%%%%%%%%%%%%%%%%%%%%%%%%%%%         ", "$$$$ $$$$$$$$$$%%%%%%%%%%%%%%%%%%%%%%%%%%%%%%%%%%%%%%%%         ", "$$$$$$$$$$$$$$$$%%%%%%%%%%%% %%%%%%%     %   %%%%%%%%%          ", "$$$$$$$$$$$$$$$$$%%%%%%%%%%  %%%%%%              %%%            ", "$$$$$$$$$$$$$$$$%%%%%%%%     %%%%%%               %%            ", "  $$$         $$%%%%%%%%                          %%       &&   ", "               $%%%%%%%%                                   &&   ", "                %%%%%%%                                         ", "                 %%%%%                                          ", "                 %%%%%                                          ", "                  %%%                                           ", "                  %%%                                           ", "                  %                                             ", "                                                                ", "                                                                ", "                                                                ", "                                                                ", "                                                                ", "                                                                ", "                                                                ", "                                                                ", "                                                                ", "                                                                "]}