{"keys": ["176", "88"], "data": {"176": {"2011": 18.740823}, "88": {"2011": 4.208272}}, "grid": ["             !!!!!!!!!!!!!!!!!!!!!!!!!!!!!!!!!!!!!!!!!!!!!!!!!!!", "              !!!!!!!!!!!!!!!!!!!!!!!!!!!!!!!!!!!!!!!!!!!!!!!!!!", "                !!!!!!!!!!!!!!!!!!!!!!!!!!!!!!!!!!!!!!!!!!!!!!!!", "                  !!!!!!!!!!!!!!!!!!!!!!!!!!!!!!!!!!!!!!!!!!!!!!", "                   !!!!!!!!!!!!!!!!!!!!!!!!!!!!!!!!!!!!!!!!!!!!!", "                     !!!!!!!!!!!!!!!!!!!!!!!!!!!!!!!!!!!!!!!!!!!", "                      !!!!!!!!!!!!!!!!!!!!!!!!!!!!!!!!!!!!!!!!!!", "                        !!!!!!!!!!!!!!!!!!!!!!!!!!!!!!!!!!!!!!!!", "                          !!!!!!!!!!!!!!!!!!!!!!!!!!!!!!!!!!!!!!", "                            !!!!!!!!!!!!!!!!!!!!!!!!!!!!!!!!!!!!", "                              !!!!!!!!!!!!!!!!!!!!!!!!!!!!!!!!!!", "                                !!!!!!!!!!!!!!!!!!!!!!!!!!!!!!!!", "                                 !!!!!!!!!!!!!!!!!!!!!!!!!!!!!!!", "                                  !!!!!!!!!!!!!!!!!!!!!!!!!!!!!!", "                                   !!!!!!!!!!!!!!!!!!!!!!!!!!!!!", "                                     !!!!!!!!!!!!!!!!!!!!!!!!!!!", "                                      !!!!!!!!!!!!!!!!!!!!!!!!!!", "                                       !!!!!!!!!!!!!!!!!!!!!!!!!", "                                        !!!!!!!!!!!!!!!!!!!!!!!!", "                                         !!!!!!!!!!!!!!!!!!!!!!!", "                                           !!!!!!!!!!!!!!!!!!!!!", "                                            !!!!!!!!!!!!!!!!!!!!", "                                             !!!!!!!!!!!!!!!!!!!", "                                              !!!!!!!!!!!!!!!!!!", "                                               !!!!!!!!!!!!!!!!!", "                                                !!!!!!!!!!!!!!!!", "                                                  !!!!!!!!!!!!!!", "                                                   !!!!!!!!!!!!!", "                                                    !!!!!!!!!!!!", "                                                     !!!!!!!!!!!", "                                                      !!!!!!!!!!", "                                                        !!!!!!!!", "                                                         !!!!!!!", "                                                          !!!!!!", "                                                           !!!!!", "                                                            !!!!", "                                                              !!", "                                                                ", "                                                                ", "                                                                ", "                                                                ", "                                                                ", "                                                                ", "                                                                ", "                                                                ", "                                                                ", "                                                                ", "                                                                ", "                                                                ", "                                                                ", "                                                                ", "                                                                ", "                                                                ", "                                                                ", "                                                                ", "                                                                ", "                                                                ", "                                                                ", "                                                                ", "                                                                ", "                                                                ", "                                                                ", "                                                                ", "                                                                "]}