{"keys": ["", "25", "215", "194", "121"], "data": {"121": {"REAL": 9.478413, "INDEX": 1.90942537087, "NAME": "Malaysia", "AREA": 32855, "REGION": 142, "LON": 102.195, "SUBREGION": 35, "ISO3": "MYS", "ISO2": "MY", "FIPS": "MY", "UN": 458, "LAT": 4.201, "POP2005": 25652985}, "215": {"REAL": 42.81091, "INDEX": 6, "NAME": "Viet Nam", "AREA": 32549, "REGION": 142, "LON": 105.314, "SUBREGION": 35, "ISO3": "VNM", "ISO2": "VN", "FIPS": "VM", "UN": 704, "LAT": 21.491, "POP2005": 85028643}, "25": {"REAL": 10.57913, "INDEX": 2.13116470275, "NAME": "Cambodia", "AREA": 17652, "REGION": 142, "LON": 104.564, "SUBREGION": 35, "ISO3": "KHM", "ISO2": "KH", "FIPS": "CB", "UN": 116, "LAT": 12.714, "POP2005": 13955507}, "194": {"REAL": 13.77714, "INDEX": 2.77540350415, "NAME": "Thailand", "AREA": 51089, "REGION": 142, "LON": 100.844, "SUBREGION": 35, "ISO3": "THA", "ISO2": "TH", "FIPS": "TH", "UN": 764, "LAT": 15.7, "POP2005": 63002911}}, "grid": ["                     !!!!!!!!!!!!!!!!!!!!!!!!!!!!!!!!!##########", "                     !!!!! !!!!!!!!!!!!!!!!!!!!!!!!!!!!#########", "                     !!!!!  !!!!!!!!!!!!!!!!!!!!!!###!!!########", "                     !!!!   !!!!!!!!!!!!!!!###!#######!!########", "                            !!!!!!!!!!!!!!!#####################", "                      !!  !!!!!!!!!!!!!!!!!!####################", "                       !  !!!!!!!!!!!!!!!!######################", "                          !!!!!!!!!!!!!!!!######################", "                           !!!     !!!##########################", "                              ###    ###########################", "                              ###     ##########################", "                               ##     ######################### ", "                               ##        #######################", "                                           #################### ", "                                           ###################  ", "                                          ##################### ", "                                         #####################  ", "                                         ####################   ", "                                         ####################   ", "                                         ###################    ", "                                         ################       ", "                                         ################       ", "                         #               #############          ", "                                         ###########            ", "                                         ########               ", "                                         #######                ", "                                        ########                ", "                                        #######                 ", "                                          #####              #  ", "                                        #####                #  ", "                                        ####                    ", "                                                                ", "                                                                ", "                                                                ", "                                                                ", "                                                                ", "                                                                ", "                                                                ", "                                                                ", "                                                                ", "                                                                ", "                                                                ", "                                                                ", "                                                                ", "                                                                ", "                                                                ", "                                                                ", "                                                                ", "                                                                ", " $$                                                             ", "$$$$                                                            ", "$$$$$                                                           ", "$$$$$$                                                          ", "$$$$$$                                                          ", "$$$$$$$                                                         ", "$$$$$$$$                                                        ", "$$$$$$$$$                                                       ", "$$$$$$$$$$%%%                                                   ", "$$$$$$$$$$%%%%                                                  ", "$$$$$$$$$$%%%%                                                  ", "$$$$$$$$$%%%%%%                                                 ", "$$$$$$$$$%%%%%%                                                 ", "$%%%%$$$%%%%%%%%%                                               ", "$%%%%%%%%%%%%%%%%%                                              "]}